setup.py
Barista.egg-info/PKG-INFO
Barista.egg-info/SOURCES.txt
Barista.egg-info/dependency_links.txt
Barista.egg-info/not-zip-safe
Barista.egg-info/requires.txt
Barista.egg-info/top_level.txt
barista/__init__.py
barista/assets.py
scripts/barista