Metadata-Version: 1.1
Name: Barista
Version: 0.0.1
Summary: A Flask application creator
Home-page: UNKNOWN
Author: Mek Karpeles
Author-email: michael.karpeles@gmail.com
License: BSD
Platform: any
Classifier: Development Status :: 2 - Pre-Alpha
Classifier: Environment :: Web Environment
Classifier: Intended Audience :: Developers
Classifier: License :: OSI Approved :: BSD License
Classifier: Operating System :: OS Independent
Classifier: Programming Language :: Python
Classifier: Topic :: Internet :: WWW/HTTP :: Dynamic Content
Classifier: Topic :: Software Development :: Libraries :: Python Modules
